flujograma/__init__.py
flujograma/diagrams_api.py
flujograma/main.py
flujograma/styles.py
flujograma/assets/arrow.png
flujograma/assets/marca-agua.png
flujograma/assets/nombre.png
flujograma/assets/fonts/ProductSans-Bold.ttf
flujograma/assets/fonts/ProductSans-Regular.ttf
flujograma/assets/icons/README.md
flujograma/assets/icons/aws/compute/ec2.png
flujograma/assets/icons/aws/database/rds.png
flujograma/assets/icons/aws/network/elb.png
flujograma/assets/icons/aws/storage/s3.png
flujograma/core/__init__.py
flujograma/core/ast_nodes.py
flujograma/core/clusters.py
flujograma/core/diagram.py
flujograma/core/edges.py
flujograma/core/layout.py
flujograma/core/nodes.py
flujograma/core/parser.py
flujograma/fonts/ProductSans-Bold.ttf.placeholder
flujograma/fonts/ProductSans-Regular.ttf.placeholder
flujograma/fonts/README.md
flujograma/languages/__init__.py
flujograma/languages/base.py
flujograma/languages/en.py
flujograma/languages/es.py
flujograma/renderers/__init__.py
flujograma/renderers/architecture_renderer.py
flujograma/renderers/pillow_renderer.py
flujograma/renderers/svg_renderer.py
flujograma-1.0.3.dist-info/licenses/LICENSE
flujograma-1.0.3.dist-info/METADATA
flujograma-1.0.3.dist-info/WHEEL
flujograma-1.0.3.dist-info/top_level.txt
flujograma-1.0.3.dist-info/RECORD
