Metadata-Version: 2.4
Name: flujograma
Version: 1.0.3
Summary: Una librería Python para crear diagramas de arquitectura y flujo con iconos profesionales
Author-email: CubeFreaKLab <cubefreaklab@gmail.com>
Maintainer-email: CubeFreaKLab <cubefreaklab@gmail.com>
License: MIT
Project-URL: Homepage, https://github.com/CubeFreaKLab/flujograma
Project-URL: Repository, https://github.com/CubeFreaKLab/flujograma.git
Project-URL: Documentation, https://github.com/CubeFreaKLab/flujograma#readme
Project-URL: Bug Tracker, https://github.com/CubeFreaKLab/flujograma/issues
Keywords: diagrams,flowchart,architecture,aws,gcp,kubernetes,visualization
Classifier: Development Status :: 4 - Beta
Classifier: Intended Audience :: Developers
Classifier: Intended Audience :: Information Technology
Classifier: Operating System :: OS Independent
Classifier: Programming Language :: Python :: 3
Classifier: Programming Language :: Python :: 3.8
Classifier: Programming Language :: Python :: 3.9
Classifier: Programming Language :: Python :: 3.10
Classifier: Programming Language :: Python :: 3.11
Classifier: Programming Language :: Python :: 3.12
Classifier: Topic :: Software Development :: Libraries :: Python Modules
Classifier: Topic :: Scientific/Engineering :: Visualization
Classifier: Topic :: System :: Systems Administration
Requires-Python: >=3.8
License-File: LICENSE
Requires-Dist: Pillow>=9.0.0
Requires-Dist: lark>=1.1.0
Provides-Extra: dev
Requires-Dist: pytest>=6.0; extra == "dev"
Requires-Dist: pytest-cov>=2.0; extra == "dev"
Requires-Dist: black>=21.0; extra == "dev"
Requires-Dist: flake8>=3.8; extra == "dev"
Requires-Dist: mypy>=0.800; extra == "dev"
Provides-Extra: build
Requires-Dist: build>=0.7.0; extra == "build"
Requires-Dist: twine>=3.0.0; extra == "build"
Dynamic: license-file
